{
  "url": "https://www.idbi.bank.in/advantage-savings-account.aspx",
  "title": "Personal & Corporate Banking | MSME & Agri banking - IDBI Bank",
  "content": "The Advantage Savings Account provides you a complete banking convenience and financial package to access your money with the ease. IDBI Bank offers you a range of savings account for optimal management of your money. With Account, you not only save your money but also make it grow.\n  * MAB – Rs. 10,000 (Metro & Urban), Rs. 5000 (Semi Urban), Rs. 2500 (Rural) and Rs. 1,000 (Rural FI).\n\n\n  * Free five ATM transactions at other Bank ATMs at Non Metro Locations\n\n\n  * Good options to grow money at attractive interest rates Instant Banking\n\n\nCall on our Phone Banking numbers Toll Free - (24x7 service) \nWhat is the minimum balance that I need to maintain in the Advantage Savings Account? \nYou need to maintain an Monthly Average Balance (MAB) of Rs. 10000 in the Advantage Savings Account for Metro & Urban Branches, Rs. 5000/- for semi urban Branches and Rs. 1000/- for Rural Branches.\nWhat is the rate of interest applicable on the Advantage Savings Account?\nInterest on Savings Bank Account is applicable as per Banks latest prevailing rate of Interest hosted on Banks website.",
  "category": "deposits",
  "page_type": "rates",
  "cta_label": "Apply Now",
  "cta_url": "https://www.idbi.bank.in/apply-now.aspx",
  "content_hash": "d84ac2d941b7f81cd606e960472e4bdbacb797c24465ebd6431444589712a11e",
  "crawled_at": "2026-07-10T12:39:20.821077Z",
  "metadata": {
    "description": "IDBI Bank",
    "keywords": null,
    "word_count": 184,
    "internal_links_count": 210,
    "external_links_count": 20
  }
}