{
  "url": "https://www.idbi.bank.in/faq-gift-card.aspx",
  "title": "Personal & Corporate Banking | MSME & Agri banking - IDBI Bank",
  "content": "* Flexibility of use - Spend the amount in any number of transactions within the validity period of the card.\n\n\n  * Validity: 2 years from the date of production of card.\n\n\n\n\nYou don’t have to be an IDBI Account holder to purchase this card. All you need to do is walk into an IDBI branch, fill out a simple application form, Pay the amount to be loaded into the card and collect your Gift Card pack instantly.\n– Full KYC needs to be submitted along with the application form.\nHow do I check the Balance remaining on my card?\nYou can walk into any IDBI ATM, insert your card, enter your PIN and do a Balance Enquiry to find out the balance remaining on your card. You can also request for a mini statement, which will give you details of the last 10 transactions on your card.\nAll you need to do is call up our 24-hour toll free number 1800-22-6999, quote your Gift Card Reference Number (account number). Your card will be deactivated immediately to prevent misuse. For more enquiries on Card may be asked on toll free number 1800-209-4324.\n  * Your card is only for your use. Please do not hand it over to anybody other than designated officers of the Bank\n  * Always sign the signature panel on the reverse of your card as soon as your receive it.\n  * Report the loss/theft/damage of the card immediately to our Phone Banking Centre 1-800-22-6999.\n\n\n  * Please do not disclose your PIN to anybody and make sure that you never keep your Gift Card and PIN together.\n  * Please memorize your PIN and destroy the enclosed PIN mailer.\n\n\nHow can I claim the unutilized balance remaining on this card?\nAs per PPI guidelines issued by RBI, for Gift cards Cash-out or refund or funds transfer shall not be permitted.\nAfter Expiry of a Gift Card, if an unspent balance is remaining in the card than the gift card may be revalidated through issuance of new Gift Card.\n\n\n  * Get your mobile number updated with Gift card customer ID.\n  * Generate the Green PIN through IDBI Bank ATM or IVR.",
  "category": "corporate",
  "page_type": "faq",
  "cta_label": "Apply Now",
  "cta_url": "https://www.idbi.bank.in/apply-now.aspx",
  "content_hash": "2e514168b81b33ce4edcc711eac147fa59b48bb2c6e2fe42d2bc1bbae7ac8aec",
  "crawled_at": "2026-07-10T12:41:01.976791Z",
  "metadata": {
    "description": "Find your answers and resolve your queries regarding gift card through IDBI bank's frequently asked question.",
    "keywords": null,
    "word_count": 360,
    "internal_links_count": 209,
    "external_links_count": 20
  }
}