{
  "url": "https://www.idbi.bank.in/fx-retail.aspx",
  "title": "Personal & Corporate Banking | MSME & Agri banking - IDBI Bank",
  "content": "FX-Retail is an electronic trading platform introduced by the Reserve Bank of India and developed by the Clearing Corporation of India Ltd. (CCIL) for Bank customers enabling them to deal in the USD/INR currency pair for their genuine forex exposures. This platform came into existence on August 05, 2019 and is available at for customers to register on the platform and use thereof. \n  * Anonymous multi-user matching system with viewing rights of CCIL’s USDINR interbank rate.\n  * Enables transactions across Individuals, Corporates, Trusts, Cooperative Banks, Foreign Portfolio Investors, Foreign Institutional Investors etc. and providing the benefit of placing the trades at the customer’s own time and convenience. Customers can currently place orders for USD/INR currency pairs only.\n  * Customers can buy or sell USD against INR for Cash, Tom and Spot delivery.\n\n\n  * Total amount of transactions is subject to limit (amount, type and tenure) assigned by the Bank.\n  * Net rate with breakup is provided to customer after factoring exchange margin and swap cost from near interbank rates.\n\n\n  * Customers to click on ‘Register Here button’ and complete the registration process by providing the required details including the IDBI Bank account details.\n  * Customers to submit complete FX-Retail activation related documents and applicable cash margin to the relationship Branch along with FX-Retail limit request.\n  * It is to be noted that the details provided by customer on FX-Retail platform need to match with those on record with the Bank for the registration request to be processed.\n  * After verification and placement of applicable cash margins, Bank sets the requested limit for the customer and the exchange mark-up on the platform.\n  * Post approval of the registration request by the customer, access credentials for the platform is shared with the customer on registered email address.\n  * After successful registration on the portal, customer can login to the FX-Retail portal from next business day. \n\n\n  * Customer can proceed to place an order on the FX-Retail platform up to the limit defined by the Bank within the limit validity period.\n  * FX-Retail shall send order confirmation mail to the customer on the registered email address upon successful completion of the order.\n  * The customer needs to contact the relationship branch immediately with this order confirmation along with necessary documents required for processing of the transaction.\n  * Customer shall ensure utilization of deals booked on the platform.\n  * In case of non-utilisation, the booked deal shall be reversed by Bank at FX card rate published by the Bank. Loss, if any, on such reversal shall be recovered from the customer’s account whereas profit on such reversals shall not be passed on to the customer and retained by the Bank.\n\n  \n| 0.0004% on the entire Transaction value in INR terms + applicable GST   |  \n| --- |  \n* Banks have also been permitted to charge their customers pre-agreed fees towards administrative expenses and mark-up (Exchange Margins) over and above the interbank rates. For further details of such charges and other terms and conditions please contact your Relationship Branch.\n*TF charges shall be as applicable. For details please contact your Relationship Branch.\n*Applicable Cash margin in the form of lien on Current Account balance/Fixed Deposit is required to be placed by the customer to enable Bank to provide requested limit, subject to the compliance of other documentation and discretion of the Bank. For further details please contact your Relationship Branch.,",
  "category": "corporate",
  "page_type": "general",
  "cta_label": "Apply Now",
  "cta_url": "https://www.idbi.bank.in/apply-now-corp.aspx",
  "content_hash": "a01694199c9564f0b180dda5bc2bac77068cfcbbef5096036beb79b2e680d0f8",
  "crawled_at": "2026-07-10T12:41:24.600100Z",
  "metadata": {
    "description": "IDBI Bank offers a wide range of products from savings and current bank account to loans for retail and msme customers  or agri loans to farmers. Apply Now.",
    "keywords": "Internet Banking, savings account, Debit Card, personal loans, home loans, loans, fixed deposits",
    "word_count": 565,
    "internal_links_count": 166,
    "external_links_count": 18
  }
}